src/__init__.py
src/compile_xml.py
src/gui.py
src/read_input_xml.py
src/xml_object.py
tests/__init__.py
tests/functional/__init__.py
tests/unit/__init__.py
tests/unit/test_compile.py
tests/unit/test_read_input_xml.py
tests/unit/test_xml_object.py
arcade_xml_generator-0.0.1.dist-info/LICENSE
arcade_xml_generator-0.0.1.dist-info/METADATA
arcade_xml_generator-0.0.1.dist-info/WHEEL
arcade_xml_generator-0.0.1.dist-info/top_level.txt
arcade_xml_generator-0.0.1.dist-info/RECORD
