Metadata-Version: 2.1
Name: arcade-xml-generator
Version: 0.0.1
Summary: GUI to load parameters into agent-based modeling with ARCADE
Author: olafc
Author-email: olafc@uw.edu
Keywords: agent-based,modeling,xml,editor,gui
Classifier: Development Status :: 1 - Planning
Classifier: Intended Audience :: Developers
Classifier: Intended Audience :: Science/Research
Classifier: Programming Language :: Python :: 3.12
Classifier: License :: OSI Approved :: MIT License
Classifier: Operating System :: Unix
Classifier: Operating System :: MacOS :: MacOS X
Classifier: Operating System :: Microsoft :: Windows
License-File: LICENSE
Requires-Dist: os
Requires-Dist: sys
Requires-Dist: xml.etree.ElementTree
Requires-Dist: PyQt5.QtCore
Requires-Dist: PyQt5.QtWidgets
Requires-Dist: logging
Requires-Dist: unittest
